ASRepCatcher/ASRepCatcher.py
ASRepCatcher/__init__.py
ASRepCatcher-0.7.0.dist-info/LICENSE
ASRepCatcher-0.7.0.dist-info/METADATA
ASRepCatcher-0.7.0.dist-info/WHEEL
ASRepCatcher-0.7.0.dist-info/entry_points.txt
ASRepCatcher-0.7.0.dist-info/top_level.txt
ASRepCatcher-0.7.0.dist-info/RECORD
